Metadata-Version: 2.1
Name: easystockplot
Version: 0.1.1
Summary: an easy stockplot package
Home-page: https://sl-huo.github.io/
Author: S Huo
Keywords: python,stock,plot
Classifier: Development Status :: 1 - Planning
Classifier: Intended Audience :: Developers
Classifier: Programming Language :: Python :: 3
Classifier: Operating System :: Unix
Classifier: Operating System :: MacOS :: MacOS X
Classifier: Operating System :: Microsoft :: Windows
License-File: LICENSE
